<?xml version="1.0" encoding="UTF-8"?>


<beans xmlns="http://www.springframework.org/schema/beans"
    xmlns:xsi="http://www.w3.org/2001/XMLSchema-instance"
    xsi:schemaLocation="
        http://www.springframework.org/schema/beans http://www.springframework.org/schema/beans/spring-beans.xsd">

    <bean id="doorBeanWithSoundAlarm" class="java_project.A_basics.alarmexample.Door">
    
      <property name="alarm" ref="soundAlarmBean"></property>
    </bean>
    
     <bean id="doorBeanWithVisualAlarm" class="java_project.A_basics.alarmexample.Door">
    
      <property name="alarm" ref="visualAlarmBean"></property>
    </bean>
    
     <bean id="soundAlarmBean" class="java_project.A_basics.alarmexample.SoundAlarm">
    
      
    </bean>
    
     <bean id="visualAlarmBean" class="java_project.A_basics.alarmexample.VisualAlarm">
    
      
    </bean>
    
    

</beans>